ndx_patterned_ogen/spec/ndx-patterned-ogen.extensions.yaml
ndx_patterned_ogen/spec/ndx-patterned-ogen.namespace.yaml
ndx_patterned_ogen/__init__.py
ndx_patterned_ogen/patterned_ogen.py
ndx_patterned_ogen-0.1.0.dist-info/METADATA
ndx_patterned_ogen-0.1.0.dist-info/WHEEL
ndx_patterned_ogen-0.1.0.dist-info/licenses/LICENSE.txt
ndx_patterned_ogen-0.1.0.dist-info/RECORD
