Metadata-Version: 2.3
Name: ndx-patterned-ogen
Version: 0.1.0
Summary: patterned (holographic) optogenetic extension to NWB standard
Author-email: Alessandra Trapani <alessandra.trapani@catalystneuro.com>
License: BSD-3
License-File: LICENSE.txt
Keywords: NWB,NeurodataWithoutBorders,ndx-extension,nwb-extension
Classifier: Intended Audience :: Developers
Classifier: Intended Audience :: Science/Research
Classifier: License :: OSI Approved :: BSD License
Classifier: Programming Language :: Python
Classifier: Programming Language :: Python :: 3.9
Classifier: Programming Language :: Python :: 3.10
Classifier: Programming Language :: Python :: 3.11
Classifier: Programming Language :: Python :: 3.12
Requires-Python: >=3.9
Requires-Dist: hdmf>=3.10.0
Requires-Dist: numpy<2.0
Requires-Dist: pynwb>=2.5.0
